uv_python_lambda/__init__.py
uv_python_lambda/py.typed
uv_python_lambda/_jsii/__init__.py
uv_python_lambda/_jsii/uv-python-lambda@0.0.7.jsii.tgz
uv_python_lambda-0.0.7.dist-info/LICENSE
uv_python_lambda-0.0.7.dist-info/METADATA
uv_python_lambda-0.0.7.dist-info/WHEEL
uv_python_lambda-0.0.7.dist-info/top_level.txt
uv_python_lambda-0.0.7.dist-info/RECORD
