Metadata-Version: 2.1
Name: uv-python-lambda
Version: 0.0.7
Summary: uv-python-lambda
Home-page: https://github.com/fourTheorem/uv-python-lambda
Author: Eoin Shanaghy<eoin.shanaghy@fourtheorem.com>
License: Apache-2.0
Project-URL: Source, https://github.com/fourTheorem/uv-python-lambda
Classifier: Intended Audience :: Developers
Classifier: Operating System :: OS Independent
Classifier: Programming Language :: JavaScript
Classifier: Programming Language :: Python :: 3 :: Only
Classifier: Programming Language :: Python :: 3.8
Classifier: Programming Language :: Python :: 3.9
Classifier: Programming Language :: Python :: 3.10
Classifier: Programming Language :: Python :: 3.11
Classifier: Typing :: Typed
Classifier: Development Status :: 5 - Production/Stable
Classifier: License :: OSI Approved
Requires-Python: ~=3.8
License-File: LICENSE
Requires-Dist: aws-cdk-lib<3.0.0,>=2.161.1
Requires-Dist: constructs<11.0.0,>=10.3.0
Requires-Dist: jsii<2.0.0,>=1.106.0
Requires-Dist: publication>=0.0.3
Requires-Dist: typeguard<4.3.0,>=2.13.3
